linggle/__init__.py
linggle/linggle_api.py
linggle/tpb_api.py
linggle/write_api.py
linggle/gec/__init__.py
linggle/gec/gec_api.py
linggle-0.0.5.dist-info/METADATA
linggle-0.0.5.dist-info/WHEEL
linggle-0.0.5.dist-info/top_level.txt
linggle-0.0.5.dist-info/RECORD
