Metadata-Version: 2.1
Name: linggle
Version: 0.0.5
Summary: This toolkit contains APIs for Linggle, LinggleGEC, LinggleWrite, and LinggleBooster.
Home-page: https://github.com/NTHU-NLPLAB/NLPLab_toolkit
Author: sappy5678, dspp779, 
Author-email: sappy@nlplab.cc, jjc@nlplab.cc, isaackch@nlplab.cc
License: UNKNOWN
Platform: UNKNOWN
Classifier: Programming Language :: Python :: 3
Classifier: Operating System :: OS Independent
Requires-Python: >=3.6
Requires-Dist: requests (>=2.22.0)
